gym_jsbsim/__init__.py
gym_jsbsim/aircraft.py
gym_jsbsim/assessors.py
gym_jsbsim/basic_ic.xml
gym_jsbsim/environment.py
gym_jsbsim/flightgear.xml
gym_jsbsim/minimal_ic.xml
gym_jsbsim/properties.py
gym_jsbsim/rewards.py
gym_jsbsim/simulation.py
gym_jsbsim/tasks.py
gym_jsbsim/utils.py
gym_jsbsim/visualiser.py
gym_jsbsim/agents/__init__.py
gym_jsbsim/agents/agents.py
gym_jsbsim/tests/__init__.py
gym_jsbsim/tests/manual_tests.py
gym_jsbsim/tests/stubs.py
gym_jsbsim/tests/test_agents.py
gym_jsbsim/tests/test_assessors.py
gym_jsbsim/tests/test_environment.py
gym_jsbsim/tests/test_functional.py
gym_jsbsim/tests/test_geodetic_position.py
gym_jsbsim/tests/test_rewards.py
gym_jsbsim/tests/test_simulation.py
gym_jsbsim/tests/test_tasks.py
gym_jsbsim/tests/test_visualiser.py
flyrl-0.2.dist-info/LICENSE
flyrl-0.2.dist-info/METADATA
flyrl-0.2.dist-info/WHEEL
flyrl-0.2.dist-info/top_level.txt
flyrl-0.2.dist-info/RECORD
